python_easy_rsa.py
python_easy_rsa-1.0.1.dist-info/LICENSE
python_easy_rsa-1.0.1.dist-info/METADATA
python_easy_rsa-1.0.1.dist-info/WHEEL
python_easy_rsa-1.0.1.dist-info/top_level.txt
python_easy_rsa-1.0.1.dist-info/RECORD
