Metadata-Version: 2.1
Name: python-easy-rsa
Version: 1.0.1
Summary: Python Easy RSA is a wrapper that allows decryption, encryption, signing, and verifying signature simpler. You can load your keys from a file or from a string. It is easy to use, fast and free!
Home-page: https://github.com/iamoracle/python-easy-rsa
Author: iamoracle
Author-email: officialbilas@gmail.com
License: MIT
Download-URL: https://github.com/iamoracle/python-easy-rsa/archive/refs/tags/v1.0.1.tar.gz
Keywords: Python,RSA,Easy,generate public key,generate private key,encrypt,decrypt,using python
Platform: UNKNOWN
Classifier: Development Status :: 3 - Alpha
Classifier: Intended Audience :: Developers
Classifier: Topic :: Software Development :: Build Tools
Classifier: License :: OSI Approved :: MIT License
Classifier: Programming Language :: Python :: 3
Classifier: Programming Language :: Python :: 3.4
Classifier: Programming Language :: Python :: 3.5
Classifier: Programming Language :: Python :: 3.6
Classifier: Programming Language :: Python :: 3.7
Classifier: Programming Language :: Python :: 3.8
Classifier: Programming Language :: Python :: 3.9
Classifier: Programming Language :: Python :: 3.10
Requires-Dist: pathlib
Requires-Dist: pycryptodome
